transpi/__init__.py
transpi/__version__.py
transpi/core.py
transpi/exception.py
transpi-0.4.0.dist-info/WHEEL
transpi-0.4.0.dist-info/METADATA
transpi-0.4.0.dist-info/RECORD
