Metadata-Version: 2.1
Name: transpi
Version: 0.4.0
Summary: Transpi is a translation tool
License: MIT
Author: ischaojie
Author-email: zhuzhezhe95@gmail.com
Requires-Python: >=3.6,<4.0
Classifier: License :: OSI Approved :: MIT License
Classifier: Programming Language :: Python :: 3
Classifier: Programming Language :: Python :: 3.6
Classifier: Programming Language :: Python :: 3.7
Classifier: Programming Language :: Python :: 3.8
Classifier: Programming Language :: Python :: 3.9
Requires-Dist: requests-html (>=0.10.0,<0.11.0)
